finanzen_fundamentals/__init__.py
finanzen_fundamentals/commodities.py
finanzen_fundamentals/etfs.py
finanzen_fundamentals/exceptions.py
finanzen_fundamentals/functions.py
finanzen_fundamentals/funds.py
finanzen_fundamentals/scraper.py
finanzen_fundamentals/search.py
finanzen_fundamentals/statics.py
finanzen_fundamentals/stocks.py
finanzen_fundamentals-0.3.3.dist-info/LICENSE
finanzen_fundamentals-0.3.3.dist-info/METADATA
finanzen_fundamentals-0.3.3.dist-info/WHEEL
finanzen_fundamentals-0.3.3.dist-info/top_level.txt
finanzen_fundamentals-0.3.3.dist-info/RECORD
