Metadata-Version: 2.1
Name: finanzen-fundamentals
Version: 0.3.3
Summary: API to fetch financial data from finanzen.net
Home-page: https://github.com/Jhruzik/Finanzen-Fundamentals
Author: Joshua Hruzik
Author-email: joshua.hruzik@gmail.com
Classifier: Programming Language :: Python :: 3
Classifier: License :: OSI Approved :: MIT License
Classifier: Operating System :: OS Independent
Classifier: Intended Audience :: Financial and Insurance Industry
Classifier: Intended Audience :: Science/Research
Classifier: Topic :: Office/Business :: Financial
Classifier: Topic :: Office/Business :: Financial :: Investment
Requires-Python: >=3.6
License-File: LICENSE
Requires-Dist: requests
Requires-Dist: beautifulsoup4
Requires-Dist: lxml
Requires-Dist: numpy
Requires-Dist: pandas
